wow_srp-0.3.0.dist-info/METADATA
wow_srp-0.3.0.dist-info/WHEEL
wow_srp-0.3.0.dist-info/license_files/LICENSE-MIT
wow_srp-0.3.0.dist-info/license_files/LICENSE-APACHE
wow_srp/__init__.py
wow_srp/__init__.pyi
wow_srp/py.typed
wow_srp/wow_srp.cpython-39-s390x-linux-gnu.so
wow_srp-0.3.0.dist-info/RECORD
