Metadata-Version: 2.1
Name: wow_srp
Version: 0.3.0
Classifier: Programming Language :: Rust
Classifier: Programming Language :: Python :: Implementation :: CPython
Classifier: Programming Language :: Python :: Implementation :: PyPy
License-File: LICENSE-MIT
License-File: LICENSE-APACHE
Summary: Cryptography library for authenticating with World of Warcraft 1.2-3.3.5 clients.
Keywords: wow,srp
Author: Gtker <github@gtker.com>
Author-email: Gtker <pip@gtker.com>
License: MIT OR Apache-2.0
Requires-Python: >=3.7
Project-URL: Source Code, https://www.github.com/gtker/wow_srp_python
